MANIFEST.in
README.rst
setup.py
django_sermon.egg-info/PKG-INFO
django_sermon.egg-info/SOURCES.txt
django_sermon.egg-info/dependency_links.txt
django_sermon.egg-info/requires.txt
django_sermon.egg-info/top_level.txt
django_sermon.egg-info/zip-safe
sermon/__init__.py
sermon/admin.py
sermon/managers.py
sermon/models.py
sermon/tests.py
sermon/urls.py
sermon/views.py
sermon/templatetags/__init__.py
sermon/templatetags/sermon.py