Metadata-Version: 1.0
Name: django-sermon
Version: 1.0.3
Summary: A simple reusable application for managing sermons in a Django application.
Home-page: http://github.com/powellc/django-sermon
Author: Colin Powell
Author-email: colin@onecardinal.com
License: BSD
Download-URL: http://github.com/powellc/django-sermon/downloads
Platform: UNKNOWN
Classifier: Development Status :: 4 - Beta
Classifier: Environment :: Web Environment
Classifier: Intended Audience :: Developers
Classifier: License :: OSI Approved :: BSD License
Classifier: Operating System :: OS Independent
Classifier: Programming Language :: Python
Classifier: Framework :: Django
